{"_id":{"$oid":"60439f79f7163f6458de8206"},"id":58,"file_location":"templates/articles/demo.html","title":"this is demo1","url_title":"demo","featured_image":"","meta_keywords":"Demo, page, djaley","meta_description":"Demo page of djaley","images":"","publish_status":true,"categories":"Hacking, Technology","views_count":0,"date_modified":{"$date":"2021-03-07T08:58:20.486Z"},"date_created":{"$date":"2021-03-06T15:27:52.991Z"},"allow_comments":true}
{"_id":{"$oid":"604bb53a89d8c84ef5d3565e"},"id":59,"file_location":"templates/articles/aj.html","title":"Swaminarayan","url_title":"aj","featured_image":"","meta_keywords":"a","meta_description":"a","images":"","publish_status":true,"categories":"","views_count":0,"date_modified":{"$date":"2021-03-13T09:27:17.605Z"},"date_created":{"$date":"2021-03-12T18:38:49.955Z"},"allow_comments":true}
{"_id":{"$oid":"606170261558d91de59f29d6"},"id":60,"file_location":"templates/articles/god.html","title":"God","url_title":"god","featured_image":"","meta_keywords":"","meta_description":"","images":null,"publish_status":true,"allow_comments":true,"categories":"","views_count":0,"date_modified":{"$date":"2021-03-29T06:13:58.262Z"},"date_created":{"$date":"2021-03-29T06:13:58.262Z"}}
